{
  "id": 99,
  "slug": "affordable-rose-bay-pest-solutions",
  "businessName": "Affordable Rose Bay Pest Solutions",
  "tradingName": "Affordable Rose Bay Pest Solutions Pty Ltd",
  "licenseNumber": "P-2024-721501",
  "licenseType": "Pest Management Technician",
  "licenseStatus": "Active",
  "licenseExpiry": "2025-11-30",
  "epaVerified": true,
  "verifiedAt": "2024-11-15",
  "phone": "02 9002 1726",
  "email": "info@affordable-rose-bay-pest-solutions.com.au",
  "website": "https://affordable-rose-bay-pest-solutions.com.au",
  "address": "126 Park Street, Rose Bay NSW",
  "suburb": "Rose Bay",
  "postcode": "2298",
  "region": "eastern",
  "description": "Expert pest control services across Rose Bay. 5+ years protecting Sydney homes and businesses.",
  "shortDescription": "Professional pest control in Rose Bay. Licensed & insured.",
  "services": [
    "bed-bug-treatment",
    "termite-treatment",
    "spider-control",
    "cockroach-control",
    "bird-control",
    "general-pest-control",
    "possum-removal"
  ],
  "serviceAreas": [
    "mosman",
    "maroubra",
    "coogee",
    "leichhardt",
    "randwick",
    "double-bay",
    "bondi-junction",
    "woollahra",
    "marrickville",
    "newtown",
    "bondi"
  ],
  "rating": 4.7,
  "reviewCount": 77,
  "yearsInBusiness": 5,
  "featured": false,
  "tier": "basic",
  "features": [
    "epa-verified",
    "warranty-guarantee",
    "licensed-insured",
    "24-7-emergency"
  ],
  "operatingHours": {
    "monday": "7:00 AM - 6:00 PM",
    "tuesday": "7:00 AM - 6:00 PM",
    "wednesday": "7:00 AM - 6:00 PM",
    "thursday": "7:00 AM - 6:00 PM",
    "friday": "7:00 AM - 6:00 PM",
    "saturday": "8:00 AM - 4:00 PM",
    "sunday": "Closed"
  },
  "pricing": {
    "generalPest": "$230 - $399",
    "termiteInspection": "$263 - $424",
    "rodentControl": "$259 - $359"
  }
}