{
  "id": 17,
  "slug": "dropdeadpest",
  "businessName": "Drop Dead Pest Control",
  "tradingName": "Drop Dead Pest Control",
  "licenseNumber": null,
  "licenseType": "Pest Management Technician",
  "licenseStatus": "Active",
  "licenseExpiry": null,
  "epaVerified": false,
  "verifiedAt": "2025-11-27",
  "phone": "02 9541 1365",
  "phoneVerified": true,
  "email": null,
  "website": "https://www.dropdeadpest.com.au",
  "websiteVerified": true,
  "address": null,
  "suburb": "Sydney CBD",
  "postcode": "2000",
  "postcodeVerified": true,
  "region": "inner-city",
  "description": "Drop Dead Pest Control offers reliable pest management services throughout Sydney. Specializing in cockroaches, ants, spiders, and rodent control.",
  "shortDescription": "Drop Dead Pest Control offers reliable pest management services throughout Sydney.",
  "services": [
    "general-pest-control"
  ],
  "serviceAreas": [
    "sydney-cbd"
  ],
  "rating": 4.6,
  "ratingSource": "Google Reviews",
  "reviewCount": 89,
  "yearsInBusiness": 12,
  "featured": false,
  "tier": "basic",
  "features": [],
  "operatingHours": null,
  "pricing": null,
  "dataQuality": {
    "score": 90,
    "verifiedFields": 12,
    "totalFields": 15,
    "issues": [],
    "lastVerified": "2025-11-27T10:34:39.847Z"
  }
}