{
  "id": 220,
  "slug": "fumapest",
  "businessName": "Fumapest Pest Control",
  "tradingName": "Fumapest Pest Control",
  "licenseNumber": null,
  "licenseType": "Pest Management Technician",
  "licenseStatus": "Active",
  "licenseExpiry": null,
  "epaVerified": false,
  "verifiedAt": "2025-11-27",
  "phone": "1300 241 500",
  "phoneVerified": true,
  "email": null,
  "website": "https://www.fumapest.com.au",
  "websiteVerified": false,
  "address": null,
  "suburb": "Padstow",
  "postcode": "2211",
  "postcodeVerified": true,
  "region": "all-sydney",
  "description": "Fumapest has been Sydney's trusted termite and pest control specialists since 1964. Expert fumigation and treatment services with over 60 years of experience.",
  "shortDescription": "Sydney's trusted termite and pest control specialists since 1964.",
  "services": [
    "termite-inspection",
    "termite-treatment",
    "general-pest-control",
    "fumigation"
  ],
  "serviceAreas": [
    "north-sydney",
    "lane-cove",
    "campbelltown",
    "manly",
    "acacia-gardens",
    "arndell-park",
    "auburn",
    "berala",
    "bidwill",
    "blackett",
    "blacktown",
    "bossley-park",
    "cabramatta",
    "cabramatta-west",
    "camellia",
    "canley-heights",
    "canley-vale",
    "clyde",
    "colebee",
    "colyton",
    "constitution-hill",
    "dean-park",
    "dharruk",
    "doonside",
    "dundas",
    "dundas-valley",
    "eastern-creek",
    "emerton",
    "ermington",
    "abbotsford",
    "ashbury",
    "ashfield",
    "balmain",
    "balmain-east",
    "birchgrove",
    "burwood",
    "burwood-heights",
    "canada-bay",
    "canterbury",
    "annangrove",
    "arcadia",
    "baulkham-hills",
    "beaumont-hills",
    "bella-vista",
    "box-hill",
    "castle-hill",
    "cattai",
    "cherrybrook",
    "dural",
    "agnes-banks",
    "north-parramatta",
    "westmead",
    "harris-park",
    "rosehill",
    "granville",
    "south-granville",
    "merrylands",
    "merrylands-west",
    "holroyd",
    "guildford",
    "guildford-west",
    "yennora",
    "fairfield-east",
    "fairfield-west",
    "fairfield-heights",
    "old-guildford",
    "smithfield",
    "wetherill-park",
    "prairiewood",
    "lansvale",
    "lidcombe",
    "regents-park",
    "silverwater",
    "newington",
    "sydney-olympic-park",
    "rydalmere",
    "telopea",
    "oatlands",
    "northmead",
    "girraween",
    "pendle-hill",
    "wentworthville",
    "old-toongabbie",
    "toongabbie",
    "winston-hills",
    "seven-hills",
    "prospect",
    "huntingwood",
    "marayong",
    "lalor-park",
    "kings-langley",
    "kings-park",
    "quakers-hill",
    "stanhope-gardens",
    "glenwood",
    "parklea",
    "kellyville-ridge",
    "the-ponds",
    "schofields",
    "riverstone",
    "marsden-park",
    "ropes-crossing",
    "st-marys",
    "north-st-marys",
    "oxley-park",
    "mount-druitt",
    "rooty-hill",
    "minchinbury",
    "woodcroft",
    "plumpton",
    "oakhurst",
    "hassall-grove",
    "shalvey",
    "lethbridge-park",
    "tregear",
    "whalan",
    "hebersham",
    "willmot",
    "kingswood",
    "werrington",
    "werrington-downs",
    "werrington-county",
    "jamisontown",
    "south-penrith",
    "penrith-south",
    "regentville",
    "leonay",
    "emu-plains",
    "emu-heights",
    "glenmore-park",
    "mulgoa",
    "wallacia",
    "luddenham",
    "orchard-hills",
    "cranebrook",
    "llandilo",
    "londonderry",
    "richmond",
    "windsor",
    "windsor-downs",
    "south-windsor",
    "mcgraths-hill",
    "vineyard",
    "oakville",
    "pitt-town",
    "pitt-town-bottoms",
    "glossodia",
    "freemans-reach",
    "wilberforce",
    "kurrajong",
    "kurrajong-heights",
    "kurmond",
    "grose-vale",
    "grose-wold",
    "north-richmond",
    "hobartville",
    "yarramundi",
    "springwood",
    "valley-heights",
    "warrimoo",
    "mount-riverview",
    "glenbrook",
    "lapstone",
    "faulconbridge",
    "linden",
    "woodford",
    "hazelbrook",
    "lawson",
    "wentworth-falls",
    "leura",
    "katoomba",
    "medlow-bath",
    "mount-victoria"
  ],
  "rating": 4.6,
  "ratingSource": "Google Reviews",
  "reviewCount": 145,
  "yearsInBusiness": 60,
  "featured": true,
  "tier": "basic",
  "features": [],
  "operatingHours": null,
  "pricing": null,
  "dataQuality": {
    "score": 95,
    "verifiedFields": 14,
    "totalFields": 15,
    "issues": [],
    "lastVerified": "2025-11-27T10:36:25.253Z"
  }
}